CHANGES.txt
CONTRIBUTORS.txt
MANIFEST.in
README.txt
setup.cfg
setup.py
Products/__init__.py
Products.Object.egg-info/PKG-INFO
Products.Object.egg-info/SOURCES.txt
Products.Object.egg-info/dependency_links.txt
Products.Object.egg-info/entry_points.txt
Products.Object.egg-info/namespace_packages.txt
Products.Object.egg-info/not-zip-safe
Products.Object.egg-info/paster_plugins.txt
Products.Object.egg-info/requires.txt
Products.Object.egg-info/top_level.txt
Products/Object/README.txt
Products/Object/__init__.py
Products/Object/config.py
Products/Object/configure.zcml
Products/Object/permissions.zcml
Products/Object/browser/__init__.py
Products/Object/browser/configure.zcml
Products/Object/content/__init__.py
Products/Object/content/configure.zcml
Products/Object/content/object.py
Products/Object/interfaces/__init__.py
Products/Object/interfaces/object.py
Products/Object/portlets/__init__.py
Products/Object/portlets/configure.zcml
Products/Object/profiles/default/factorytool.xml
Products/Object/profiles/default/metadata.xml
Products/Object/profiles/default/portlets.xml
Products/Object/profiles/default/rolemap.xml
Products/Object/profiles/default/types.xml
Products/Object/profiles/default/types/Object.xml
Products/Object/tests/__init__.py
Products/Object/tests/base.py
Products/Object/tests/test_doctest.py
docs/HISTORY.txt
docs/INSTALL.txt
docs/LICENSE.GPL
docs/LICENSE.txt