Metadata-Version: 1.0
Name: Products.Object
Version: 0.9
Summary: Content type to describe a physical object
Home-page: http://svn.plone.org/svn/collective/
Author: David Jonas
Author-email: davidjonasdesign@gmail.com
License: GPL
Keywords: contenttype archetypes
Platform: UNKNOWN
Classifier: Framework :: Plone
Classifier: Intended Audience :: Developers
Classifier: License :: OSI Approved :: GNU General Public License (GPL)
